scDesign3Py/__init__.py
scDesign3Py/_core.py
scDesign3Py/_utils/_errors.py
scDesign3Py/_utils/_format.py
scDesign3Py/tools/get_bpparam.py
scDesign3Py/tools/lrt.py
scDesign3Py/tools/plot.py
scDesign3Py-1.0.0.dist-info/LICENSE
scDesign3Py-1.0.0.dist-info/METADATA
scDesign3Py-1.0.0.dist-info/WHEEL
scDesign3Py-1.0.0.dist-info/top_level.txt
scDesign3Py-1.0.0.dist-info/RECORD
