Metadata-Version: 2.1
Name: scDesign3Py
Version: 1.0.0
Summary: The python interface for scDesign3 R package.
Author-email: Di Liu <liudi654@gmail.com>
License: MIT License
Project-URL: Homepage, https://github.com/DILIU899/scDesign3Py/
Classifier: License :: OSI Approved :: MIT License
Classifier: Programming Language :: Python :: 3
Classifier: Operating System :: OS Independent
Requires-Python: >=3.9
License-File: LICENSE
Requires-Dist: numpy
Requires-Dist: pandas
Requires-Dist: rpy2
Requires-Dist: anndata
Requires-Dist: matplotlib
Requires-Dist: seaborn
